gt_sat_api/__init__.py
gt_sat_api/utils.py
gt_sat_api/models/__init__.py
gt_sat_api/models/anulacion_dte.py
gt_sat_api/models/complemento.py
gt_sat_api/models/direccion.py
gt_sat_api/models/dte.py
gt_sat_api/models/emisor.py
gt_sat_api/models/frase.py
gt_sat_api/models/impuesto.py
gt_sat_api/models/item.py
gt_sat_api/models/receptor.py
gt_sat_api/models/total_impuesto.py
gt_sat_api/parsers/__init__.py
gt_sat_api/parsers/dte_to_xml.py
gt_sat_api/parsers/dte_to_xml_annulled.py
gt_sat_api/templates/AnulacionDTE.xml.jinja
gt_sat_api/templates/Factura.xml.jinja
gt_sat_api/templates/__init__.py
tests/examples/Anulado.xml
tests/examples/Factura.xml
tests/examples/FacturaCambiaria.xml
tests/examples/FacturaPeqContr.xml
tests/examples/__init__.py
gt_sat_api-1.22.0.dist-info/METADATA
gt_sat_api-1.22.0.dist-info/WHEEL
gt_sat_api-1.22.0.dist-info/top_level.txt
gt_sat_api-1.22.0.dist-info/RECORD
