Metadata-Version: 2.1
Name: gt-sat-api
Version: 1.22.0
Summary: GT SAT API
Home-page: https://gitlab.com/HomebrewSoft/l10n_gt/gt_sat_api
Author: HomebrewSoft
Author-email: moises@homebrewsoft.dev
License: MIT
Platform: UNKNOWN
